bricks/__init__.py
bricks/state.py
bricks/client/__init__.py
bricks/client/manage.py
bricks/client/runner.py
bricks/client/server/__init__.py
bricks/client/server/sanic_.py
bricks/client/server/starlette_.py
bricks/core/__init__.py
bricks/core/context.py
bricks/core/dispatch.py
bricks/core/events.py
bricks/core/genesis.py
bricks/core/signals.py
bricks/db/__init__.py
bricks/db/mongo.py
bricks/db/redis_.py
bricks/db/rocksdb.py
bricks/db/sqlite.py
bricks/downloader/__init__.py
bricks/downloader/cffi.py
bricks/downloader/curl.py
bricks/downloader/dp.py
bricks/downloader/go_requests.py
bricks/downloader/httpx_.py
bricks/downloader/playwright_.py
bricks/downloader/pyhttpx_.py
bricks/downloader/requests_.py
bricks/downloader/tls_client_.py
bricks/lib/__init__.py
bricks/lib/cookies.py
bricks/lib/counter.py
bricks/lib/extractors.py
bricks/lib/headers.py
bricks/lib/items.py
bricks/lib/nodes.py
bricks/lib/proxies.py
bricks/lib/request.py
bricks/lib/response.py
bricks/lib/variable.py
bricks/lib/queues/__init__.py
bricks/lib/queues/cache.py
bricks/lib/queues/local.py
bricks/lib/queues/redis_.py
bricks/lib/queues/rocksdb_.py
bricks/lib/queues/smart.py
bricks/lib/queues/sqlite_.py
bricks/plugins/__init__.py
bricks/plugins/make_seeds.py
bricks/plugins/on_request.py
bricks/plugins/scripts.py
bricks/plugins/storage.py
bricks/rpc/__init__.py
bricks/rpc/common.py
bricks/rpc/grpc_/__init__.py
bricks/rpc/grpc_/generic_pb2.py
bricks/rpc/grpc_/generic_pb2.pyi
bricks/rpc/grpc_/generic_pb2_grpc.py
bricks/rpc/grpc_/service.py
bricks/rpc/http_/__init__.py
bricks/rpc/http_/service.py
bricks/rpc/redis_/__init__.py
bricks/rpc/redis_/service.py
bricks/rpc/socket_/__init__.py
bricks/rpc/socket_/service.py
bricks/rpc/websocket_/__init__.py
bricks/rpc/websocket_/service.py
bricks/spider/__init__.py
bricks/spider/addon.py
bricks/spider/air.py
bricks/spider/form.py
bricks/spider/template.py
bricks/tpls/__init__.py
bricks/tpls/spider/__init__.py
bricks/tpls/spider/form.tpl
bricks_py-0.1.4.dist-info/licenses/LICENSE
bricks_py-0.1.4.dist-info/METADATA
bricks_py-0.1.4.dist-info/WHEEL
bricks_py-0.1.4.dist-info/top_level.txt
bricks_py-0.1.4.dist-info/RECORD
