Metadata-Version: 2.4
Name: bricks_py
Version: 0.1.4
Summary: quickly build your crawler
Home-page: https://github.com/KKKKKKKEM/bricks.git
Author: Kem
Author-email: 531144129@qq.com
License: MIT
Keywords: bricks
Requires-Python: >=3.8.0
License-File: LICENSE
Requires-Dist: loguru==0.7.3
Requires-Dist: jmespath-community==1.1.3
Requires-Dist: lxml==5.3.1
Requires-Dist: jsonpath==0.82.2
Requires-Dist: w3lib==2.3.1
Requires-Dist: curl_cffi==0.13.0
Requires-Dist: redis==5.2.1
Requires-Dist: better_exceptions==0.3.3
Dynamic: author
Dynamic: author-email
Dynamic: description
Dynamic: description-content-type
Dynamic: home-page
Dynamic: keywords
Dynamic: license
Dynamic: license-file
Dynamic: requires-dist
Dynamic: requires-python
Dynamic: summary
